odoo/addons/product_expiry_assign/README.rst
odoo/addons/product_expiry_assign/__init__.py
odoo/addons/product_expiry_assign/__manifest__.py
odoo/addons/product_expiry_assign/i18n/it.po
odoo/addons/product_expiry_assign/i18n/product_expiry_assign.pot
odoo/addons/product_expiry_assign/models/__init__.py
odoo/addons/product_expiry_assign/models/res_company.py
odoo/addons/product_expiry_assign/models/res_config_settings.py
odoo/addons/product_expiry_assign/models/stock_quant.py
odoo/addons/product_expiry_assign/readme/CONTRIBUTORS.md
odoo/addons/product_expiry_assign/readme/DESCRIPTION.md
odoo/addons/product_expiry_assign/readme/USAGE.md
odoo/addons/product_expiry_assign/static/description/icon.png
odoo/addons/product_expiry_assign/static/description/index.html
odoo/addons/product_expiry_assign/tests/__init__.py
odoo/addons/product_expiry_assign/tests/test_ignore_expiration_date.py
odoo/addons/product_expiry_assign/views/res_config_settings.xml
odoo_addon_product_expiry_assign-18.0.1.0.0.4.dist-info/METADATA
odoo_addon_product_expiry_assign-18.0.1.0.0.4.dist-info/WHEEL
odoo_addon_product_expiry_assign-18.0.1.0.0.4.dist-info/top_level.txt
odoo_addon_product_expiry_assign-18.0.1.0.0.4.dist-info/RECORD
